antoni_baczynski/__init__.py
antoni_baczynski/main.py
antoni_baczynski-0.1.0.dist-info/LICENSE
antoni_baczynski-0.1.0.dist-info/METADATA
antoni_baczynski-0.1.0.dist-info/WHEEL
antoni_baczynski-0.1.0.dist-info/top_level.txt
antoni_baczynski-0.1.0.dist-info/RECORD
