Metadata-Version: 2.2
Name: antoni_baczynski
Version: 0.1.0
Summary: Przykładowy pakiet o nazwie antoni_baczynski do publikacji na PyPI
Author-email: Antoni Baczyński <twojemail@example.com>
License: MIT License
Project-URL: Homepage, https://github.com/twoje_repo
Project-URL: Bug Tracker, https://github.com/twoje_repo/issues
Requires-Python: >=3.7
License-File: LICENSE
